pkg_trainmote/__init__.py
pkg_trainmote/apiController.py
pkg_trainmote/authentication.py
pkg_trainmote/baseAPI.py
pkg_trainmote/bluetoothservice.py
pkg_trainmote/configApiController.py
pkg_trainmote/configControllerModule.py
pkg_trainmote/databaseControllerModule.py
pkg_trainmote/deviceApiController.py
pkg_trainmote/deviceController.py
pkg_trainmote/gpioservice.py
pkg_trainmote/libInstaller.py
pkg_trainmote/powerControllerModule.py
pkg_trainmote/programApiController.py
pkg_trainmote/programController.py
pkg_trainmote/programMachine.py
pkg_trainmote/stateControllerModule.py
pkg_trainmote/stopPointApiController.py
pkg_trainmote/switchApiController.py
pkg_trainmote/trainmote.py
pkg_trainmote/traintrackingservice.py
pkg_trainmote/userHelper.py
pkg_trainmote/actions/actionHelper.py
pkg_trainmote/actions/actionInterface.py
pkg_trainmote/actions/clockAction.py
pkg_trainmote/actions/setStopAction.py
pkg_trainmote/actions/setSwitchAction.py
pkg_trainmote/actions/timerAction.py
pkg_trainmote/models/Action.py
pkg_trainmote/models/CommandModel.py
pkg_trainmote/models/CommandResultModel.py
pkg_trainmote/models/ConfigModel.py
pkg_trainmote/models/GPIORelaisModel.py
pkg_trainmote/models/Program.py
pkg_trainmote/models/User.py
pkg_trainmote/models/__init__.py
pkg_trainmote/schemes/config_scheme.json
pkg_trainmote/schemes/program_scheme.json
pkg_trainmote/schemes/program_update_scheme.json
pkg_trainmote/schemes/stop_scheme.json
pkg_trainmote/schemes/stop_update_scheme.json
pkg_trainmote/schemes/switch_scheme.json
pkg_trainmote/schemes/switch_update_scheme.json
pkg_trainmote/scripts/updateScript.sh
pkg_trainmote/validators/pinValidator.py
pkg_trainmote/validators/validator.py
trainmote_module_felix_nievelstein_de-0.5.32.dist-info/LICENSE
trainmote_module_felix_nievelstein_de-0.5.32.dist-info/METADATA
trainmote_module_felix_nievelstein_de-0.5.32.dist-info/WHEEL
trainmote_module_felix_nievelstein_de-0.5.32.dist-info/entry_points.txt
trainmote_module_felix_nievelstein_de-0.5.32.dist-info/top_level.txt
trainmote_module_felix_nievelstein_de-0.5.32.dist-info/RECORD
