Metadata-Version: 2.1
Name: trainmote-module-felix-nievelstein-de
Version: 0.5.32
Summary: Application to create a web server to control a model train environment
Home-page: https://github.com/FelixNievelstein/Trainmote-Server
Author: Felix Nievelstein
Author-email: app@felix-nievelstein.de
License: UNKNOWN
Platform: UNKNOWN
Classifier: Programming Language :: Python :: 3
Classifier: License :: OSI Approved :: MIT License
Classifier: Operating System :: POSIX :: Linux
Requires-Python: >=3, <4
Requires-Dist: adafruit-circuitpython-ads1x15
Requires-Dist: PyBluez
Requires-Dist: RPI.GPIO
Requires-Dist: adafruit-blinka
Requires-Dist: flask
Requires-Dist: jsonschema
Requires-Dist: Flask-HTTPAuth
Requires-Dist: python-statemachine
